django_appgen/__init__.py
django_appgen/cli.py
mon_app/__init__.py
mon_app/admin.py
mon_app/apps.py
mon_app/tests.py
mon_app/urls.py
mon_app/migrations/__init__.py
mon_app/models/__init__.py
mon_app/views/__init__.py
djappgen-0.1.dist-info/METADATA
djappgen-0.1.dist-info/WHEEL
djappgen-0.1.dist-info/entry_points.txt
djappgen-0.1.dist-info/top_level.txt
djappgen-0.1.dist-info/RECORD
